wtforms_jsonschema2/__init__.py
wtforms_jsonschema2/base.py
wtforms_jsonschema2/exceptions.py
wtforms_jsonschema2/fab.py
wtforms_jsonschema2-0.1.0.dist-info/METADATA
wtforms_jsonschema2-0.1.0.dist-info/RECORD
wtforms_jsonschema2-0.1.0.dist-info/WHEEL
wtforms_jsonschema2-0.1.0.dist-info/top_level.txt
