Metadata-Version: 2.1
Name: wtforms-jsonschema2
Version: 0.1.0
Summary: Package to convert WTForms to JSON Schema
Home-page: https://github.com/dolfandringa/wtforms_jsonschema
Author: Dolf Andringa
Author-email: dolfandringa@gmail.com
License: UNKNOWN
Project-URL: Source, https://github.com/dolfandringa/wtforms_jsonschema/
Keywords: wtforms jsonschema
Platform: UNKNOWN
Classifier: Programming Language :: Python :: 3
Classifier: Development Status :: 3 - Alpha
Classifier: License :: OSI Approved :: MIT License
Provides-Extra: fab
Provides-Extra: test
Requires-Dist: wtforms
Provides-Extra: fab
Requires-Dist: flask-appbuilder; extra == 'fab'
Provides-Extra: test
Requires-Dist: pytest; extra == 'test'
Requires-Dist: pytest-cov; extra == 'test'
